infostat/__init__.py
infostat-0.0.0.dist-info/METADATA
infostat-0.0.0.dist-info/WHEEL
infostat-0.0.0.dist-info/top_level.txt
infostat-0.0.0.dist-info/RECORD
